pycoeus/__init__.py
pycoeus/features.py
pycoeus/logging_config.py
pycoeus/main.py
pycoeus/utils/datasets.py
pycoeus/utils/generate_labels.py
pycoeus/utils/geospatial.py
pycoeus/utils/io.py
pycoeus/utils/models.py
pycoeus/utils/monochromize.py
pycoeus/utils/performance_metrics.py
pycoeus/utils/train_model.py
pycoeus-0.6.0.dist-info/licenses/LICENSE
pycoeus-0.6.0.dist-info/licenses/NOTICE
pycoeus-0.6.0.dist-info/METADATA
pycoeus-0.6.0.dist-info/WHEEL
pycoeus-0.6.0.dist-info/top_level.txt
pycoeus-0.6.0.dist-info/RECORD
