Metadata-Version: 2.4
Name: pycoeus
Version: 0.6.0
Summary: Segment (georeferenced) raster data in an interactive fashion. Retrain models in seconds. Only small amounts of labeled data necessary because of our use of pretrained base models as feature extractors.
Author-email: Christiaan Meijer <c.meijer@esciencecenter.nl>
License:                                  Apache License
Project-URL: Repository, https://github.com/DroneML/pycoeus
Project-URL: Issues, https://github.com/DroneML/pycoeus/issues
Project-URL: ReadTheDocs, https://pycoeus.readthedocs.io
Keywords: Segmentation, UNet, Active learning, Drone, Raster data, Spatial data
Classifier: Development Status :: 2 - Pre-Alpha
Classifier: Intended Audience :: Developers
Classifier: Intended Audience :: Science/Research
Classifier: Natural Language :: English
Classifier: Programming Language :: Python :: 3
Classifier: Programming Language :: Python :: 3.10
Classifier: Programming Language :: Python :: 3.11
Classifier: Programming Language :: Python :: 3.12
Requires-Python: >=3.10
License-File: LICENSE
License-File: NOTICE
Requires-Dist: dask
Requires-Dist: tqdm
Requires-Dist: numpy
Requires-Dist: pandas
Requires-Dist: rasterio
Requires-Dist: scikit-learn
Requires-Dist: torch
Requires-Dist: torchvision
Requires-Dist: torchinfo
Requires-Dist: geopandas
Requires-Dist: rioxarray
Requires-Dist: huggingface_hub
Requires-Dist: xgboost
Requires-Dist: wget
Provides-Extra: train
Requires-Dist: torch; extra == "train"
Requires-Dist: pillow; extra == "train"
Requires-Dist: torchvision; extra == "train"
Requires-Dist: mlflow; extra == "train"
Provides-Extra: dev
Requires-Dist: build; extra == "dev"
Requires-Dist: bump-my-version; extra == "dev"
Requires-Dist: coverage[toml]; extra == "dev"
Requires-Dist: pytest; extra == "dev"
Requires-Dist: pytest-cov; extra == "dev"
Requires-Dist: ruff; extra == "dev"
Requires-Dist: sphinx; extra == "dev"
Requires-Dist: sphinx_rtd_theme; extra == "dev"
Requires-Dist: sphinx-autoapi; extra == "dev"
Requires-Dist: tox; extra == "dev"
Requires-Dist: myst_parser; extra == "dev"
Provides-Extra: docs
Requires-Dist: sphinx; extra == "docs"
Requires-Dist: sphinx_rtd_theme; extra == "docs"
Requires-Dist: sphinx-autoapi; extra == "docs"
Requires-Dist: myst_parser; extra == "docs"
Provides-Extra: publishing
Requires-Dist: build; extra == "publishing"
Requires-Dist: twine; extra == "publishing"
Requires-Dist: wheel; extra == "publishing"
Dynamic: license-file
